{
  "60": {
    "inputs": {
      "ckpt_name": "juggerinpaint.safetensors",
      "key_opt": "",
      "mode": "Auto"
    },
    "class_type": "CheckpointLoaderSimpleShared //Inspire",
    "_meta": {
      "title": "Shared Checkpoint Loader (Inspire)"
    }
  },
  "77": {
    "inputs": {
      "samples": [
        "Sampler",
        0
      ],
      "vae": [
        "60",
        2
      ]
    },
    "class_type": "VAEDecode",
    "_meta": {
      "title": "VAE Decode"
    }
  },
  "107": {
    "inputs": {
      "grow_mask_by": 30,
      "pixels": [
        "Image_loader",
        0
      ],
      "vae": [
        "60",
        2
      ],
      "mask": [
        "Mask_loader",
        0
      ]
    },
    "class_type": "VAEEncodeForInpaint",
    "_meta": {
      "title": "VAE Encode (for Inpainting)"
    }
  },
  "112": {
    "inputs": {
      "images": [
        "77",
        0
      ]
    },
    "class_type": "PreviewImage",
    "_meta": {
      "title": "Preview Image"
    }
  },
  "Image_loader": {
    "inputs": {
      "image": ""
    },
    "class_type": "ETN_LoadImageBase64",
    "_meta": {
      "title": "Load Image (Base64)"
    }
  },
  "Mask_loader": {
    "inputs": {
      "mask": ""
    },
    "class_type": "ETN_LoadMaskBase64",
    "_meta": {
      "title": "Load Mask (Base64)"
    }
  },
  "Prompt": {
    "inputs": {
      "text": "a lion, high quality, hd",
      "clip": [
        "60",
        1
      ]
    },
    "class_type": "CLIPTextEncode",
    "_meta": {
      "title": "CLIP Text Encode (Prompt)"
    }
  },
  "Negative_prompt": {
    "inputs": {
      "text": "embedding:negativeXL_A , blurry, lowres",
      "clip": [
        "60",
        1
      ]
    },
    "class_type": "CLIPTextEncode",
    "_meta": {
      "title": "CLIP Text Encode (Prompt)"
    }
  },
  "Sampler": {
    "inputs": {
      "add_noise": "enable",
      "noise_seed": 832226232568812,
      "steps": 30,
      "cfg": 4,
      "sampler_name": "dpmpp_3m_sde_gpu",
      "scheduler": "karras",
      "start_at_step": 0,
      "end_at_step": 10000,
      "return_with_leftover_noise": "disable",
      "model": [
        "60",
        0
      ],
      "positive": [
        "Prompt",
        0
      ],
      "negative": [
        "Negative_prompt",
        0
      ],
      "latent_image": [
        "107",
        0
      ]
    },
    "class_type": "KSamplerAdvanced",
    "_meta": {
      "title": "KSampler (Advanced)"
    }
  }
}